{
	"ident": 1069,
	"order": 23,
	"objtype": "kRadioGroup",
	"properties": {
		"active": true,
		"align": "kLeftJst",
		"alpha": 255,
		"backcolor": "kColorDefault",
		"backgroundtheme": "kBGThemeParent",
		"backpattern": 0,
		"bordercolor": "kColorDefault",
		"buttoncnt": 3,
		"candropcursor": 0,
		"columncnt": 1,
		"contextmenu": "",
		"cursor": 0,
		"dataname": "",
		"desgroup": 0,
		"designactive": true,
		"deslock": false,
		"disablefocus": false,
		"dragborder": false,
		"dragiconid": 0,
		"dragmode": "kNoDragging",
		"dragrange": "kRangeAll",
		"dropmode": "kAcceptNone",
		"edgefloat": "kEFnone",
		"enabled": true,
		"fieldstyle": "CtrlRadioButton",
		"font": 5,
		"fontsize": 10,
		"fontstyle": "kPlain",
		"forecolor": "kColorDefault",
		"height": 61,
		"helpfile": 0,
		"horizontal": false,
		"iconid": 0,
		"keyevents": false,
		"left": 312,
		"mouseevents": false,
		"nodropcursor": 0,
		"nogray": false,
		"objlink": 0,
		"rmouseevents": false,
		"statusevents": false,
		"subwindowstyle": false,
		"text": {
			"type": 0,
			"calc": "Item 1,Item 2,Item 3"
		},
		"textcolor": "kColorDefault",
		"tooltip": {
			"type": 0,
			"calc": "Radio Group"
		},
		"top": 338,
		"userinfo": "",
		"visible": true,
		"width": 93
	}
}
