{
	"ident": 1044,
	"order": 28,
	"objtype": "kComponent",
	"componentlib": "Document Viewer Library",
	"componentctrl": "Rtf Viewer",
	"properties": {
		"active": true,
		"alpha": 255,
		"candropcursor": 0,
		"contextmenu": "",
		"cursor": 0,
		"dataname": "",
		"desgroup": 0,
		"designactive": true,
		"deslock": false,
		"disablefocus": false,
		"disablesystemfocus": false,
		"dragborder": false,
		"dragiconid": 0,
		"dragmode": "kNoDragging",
		"dragrange": "kRangeAll",
		"dropmode": "kAcceptNone",
		"edgefloat": "kEFnone",
		"effect": "kBorderNone",
		"enabled": true,
		"fieldstyle": "CtrlListBox",
		"filename": "file:///",
		"height": 120,
		"helpfile": 0,
		"horzscroll": true,
		"keyevents": false,
		"left": 374,
		"mouseevents": false,
		"nodropcursor": 0,
		"objlink": 0,
		"rmouseevents": false,
		"statusevents": false,
		"tooltip": "",
		"top": 398,
		"userinfo": "",
		"vertscroll": true,
		"visible": true,
		"width": 120
	}
}
